indipyweb/__init__.py
indipyweb/__main__.py
indipyweb/iclient.py
indipyweb/web/__init__.py
indipyweb/web/app.py
indipyweb/web/device.py
indipyweb/web/edit.py
indipyweb/web/setup.py
indipyweb/web/userdata.py
indipyweb/web/vector.py
indipyweb/web/static/favicon.ico
indipyweb/web/static/htmx.min.js
indipyweb/web/static/indipyweb.css
indipyweb/web/static/indipyweb.js
indipyweb/web/static/sse.js
indipyweb/web/static/w3-colors-flat.css
indipyweb/web/static/w3.css
indipyweb/web/templates/blobs.html
indipyweb/web/templates/devicepage.html
indipyweb/web/templates/group.html
indipyweb/web/templates/image.html
indipyweb/web/templates/instruments.html
indipyweb/web/templates/landing.html
indipyweb/web/templates/messages.html
indipyweb/web/templates/notfound.html
indipyweb/web/templates/edit/loggedout.html
indipyweb/web/templates/edit/login.html
indipyweb/web/templates/edit/max_header.html
indipyweb/web/templates/edit/min_header.html
indipyweb/web/templates/edit/admin/adminedit.html
indipyweb/web/templates/edit/admin/editoptions.html
indipyweb/web/templates/edit/admin/edituser.html
indipyweb/web/templates/edit/admin/listusers.html
indipyweb/web/templates/edit/admin/optionsdelete.html
indipyweb/web/templates/edit/user/userdeleted.html
indipyweb/web/templates/edit/user/useredit.html
indipyweb/web/templates/setup/blobfolder.html
indipyweb/web/templates/setup/indihost.html
indipyweb/web/templates/setup/indiport.html
indipyweb/web/templates/setup/setuppage.html
indipyweb/web/templates/setup/webhost.html
indipyweb/web/templates/setup/webport.html
indipyweb/web/templates/vector/blobmember.html
indipyweb/web/templates/vector/getvector.html
indipyweb/web/templates/vector/lightmember.html
indipyweb/web/templates/vector/numbermember.html
indipyweb/web/templates/vector/numbervalues.html
indipyweb/web/templates/vector/result.html
indipyweb/web/templates/vector/state.html
indipyweb/web/templates/vector/switchmember.html
indipyweb/web/templates/vector/textmember.html
indipyweb-0.1.4.dist-info/entry_points.txt
indipyweb-0.1.4.dist-info/licenses/LICENSE
indipyweb-0.1.4.dist-info/WHEEL
indipyweb-0.1.4.dist-info/METADATA
indipyweb-0.1.4.dist-info/RECORD
