Metadata-Version: 2.4
Name: indipyweb
Version: 0.1.4
Summary: Web server to communicate to an INDI service.
Keywords: indi,client,astronomy,instrument
Author-email: Bernard Czenkusz <bernie@skipole.co.uk>
Requires-Python: >=3.10
Classifier: License :: OSI Approved :: MIT License
Classifier: Topic :: Scientific/Engineering :: Astronomy
Classifier: Topic :: Scientific/Engineering :: Interface Engine/Protocol Translator
License-File: LICENSE
Requires-Dist: indipyclient>=0.9.1
Requires-Dist: litestar[standard]>=2.18.0
Requires-Dist: litestar[mako]>=2.18.0
Requires-Dist: sniffio>=1.3.1
Project-URL: Source, https://github.com/bernie-skipole/indipyweb
